LICENSE
README.md
pyproject.toml
setup.cfg
setup.py
py_simple_report/__init__.py
py_simple_report/__version__.py
py_simple_report/main.py
py_simple_report/utils.py
py_simple_report/variables.py
py_simple_report/vis_utils.py
py_simple_report.egg-info/PKG-INFO
py_simple_report.egg-info/SOURCES.txt
py_simple_report.egg-info/dependency_links.txt
py_simple_report.egg-info/requires.txt
py_simple_report.egg-info/top_level.txt